main.py
setup.py
fedlearnerr.egg-info/PKG-INFO
fedlearnerr.egg-info/SOURCES.txt
fedlearnerr.egg-info/dependency_links.txt
fedlearnerr.egg-info/requires.txt
fedlearnerr.egg-info/top_level.txt